PyIndi/_PyIndi.cpython-39-aarch64-linux-gnu.so
PyIndi/__init__.py
pyindi_client.libs/libcfitsio-b4d95be1.so.2.3.37
pyindi_client.libs/libindiclient-be301c53.so.2.1.2
pyindi_client.libs/libnova-0-a94e5120.15.so.0.0.0
pyindi_client-2.2.0.dist-info/METADATA
pyindi_client-2.2.0.dist-info/WHEEL
pyindi_client-2.2.0.dist-info/top_level.txt
pyindi_client-2.2.0.dist-info/RECORD
pyindi_client-2.2.0.dist-info/licenses/LICENSE
pyindi_client-2.2.0.dist-info/sboms/auditwheel.cdx.json
