Metadata-Version: 2.4
Name: pyindi-client
Version: 2.2.0
Summary: Third party Python API for INDI client
Author-email: geehalel <geehalel@gmail.com>
Project-URL: Homepage, https://github.com/indilib/pyindi-client
Project-URL: Bug Tracker, https://github.com/indilib/pyindi-client/issues
Classifier: License :: OSI Approved :: GNU General Public License v3 or later (GPLv3+)
Classifier: Natural Language :: English
Classifier: Programming Language :: Python
Classifier: Operating System :: Unix
Classifier: Intended Audience :: Science/Research
Classifier: Topic :: Scientific/Engineering :: Astronomy
Requires-Python: >=3.7
License-File: LICENSE
Requires-Dist: requests
Requires-Dist: bottle
Requires-Dist: dbus-python
Dynamic: license-file
